{
  "schema": "massentest_quality_snapshot_v1",
  "generated_at": "2026-07-01 18:25:19.252",
  "app_version": "4.0.0-alpha Build 16",
  "document_count": 128,
  "ampel": {
    "gruen": 46,
    "gelb": 35,
    "rot": 47
  },
  "documents": {
    "mt-0001-13042026-m-ssen-vermieter-eigenbedarf-begr-nden-": {
      "datei": "13042026_Müssen Vermieter Eigenbedarf begründen Prinzipiell besc.pdf",
      "status": "bestanden",
      "sollfelder": 2,
      "abweichungen": 0,
      "fields": {
        "Neuer Dateiname": "ok",
        "Dokumenttyp": "ok"
      }
    },
    "mt-0002-29032026-alarmanlagen-video-berwachnung-tresore-": {
      "datei": "29032026__Alarmanlagen Videoüberwachnung _Tresore Wertschutzschr.pdf",
      "status": "abweichung",
      "sollfelder": 4,
      "abweichungen": 3,
      "fields": {
        "Neuer Dateiname": "abweichung",
        "Lieferant": "abweichung",
        "Dokumenttyp": "abweichung",
        "LIEFERSCHEINNR": "ok"
      }
    },
    "mt-0003-absender-anderes-pdf": {
      "datei": "Absender Anderes.pdf",
      "status": "bestanden",
      "sollfelder": 2,
      "abweichungen": 0,
      "fields": {
        "Neuer Dateiname": "ok",
        "Dokumenttyp": "ok"
      }
    },
    "mt-0004-aida-cruises-am-anderes-12-07-2023-pdf": {
      "datei": "AIDA Cruises _ Am Anderes 12.07.2023.pdf",
      "status": "bestanden",
      "sollfelder": 6,
      "abweichungen": 0,
      "fields": {
        "Neuer Dateiname": "ok",
        "Lieferant": "ok",
        "Dokumenttyp": "ok",
        "Dokumentdatum": "ok",
        "RECHNR": "ok",
        "GESAMTBETRAG": "ok"
      }
    },
    "mt-0005-allianz-lebensversicherungs-ag-information-22-08": {
      "datei": "Allianz Lebensversicherungs-AG Information 22.08.2022.pdf",
      "status": "abweichung",
      "sollfelder": 5,
      "abweichungen": 2,
      "fields": {
        "Neuer Dateiname": "abweichung",
        "Lieferant": "ok",
        "Dokumenttyp": "ok",
        "Dokumentdatum": "ok",
        "VERSICHERUNGSNR": "abweichung"
      }
    },
    "mt-0006-amtsgericht-anderes-26-02-2020-pdf": {
      "datei": "Amtsgericht Anderes 26.02.2020.pdf",
      "status": "abweichung",
      "sollfelder": 4,
      "abweichungen": 3,
      "fields": {
        "Neuer Dateiname": "abweichung",
        "Lieferant": "abweichung",
        "Dokumenttyp": "abweichung",
        "Dokumentdatum": "ok"
      }
    },
    "mt-0007-anderes-18-01-2023-pdf": {
      "datei": "Anderes 18.01.2023.pdf",
      "status": "abweichung",
      "sollfelder": 8,
      "abweichungen": 1,
      "fields": {
        "Neuer Dateiname": "ok",
        "Lieferant": "ok",
        "Dokumenttyp": "ok",
        "Dokumentdatum": "ok",
        "RECHNR": "ok",
        "AKTENZEICHEN": "abweichung",
        "VERSICHERUNGSNR": "ok",
        "GESAMTBETRAG": "ok"
      }
    },
    "mt-0008-anleitung-scansnap-pdf": {
      "datei": "Anleitung Scansnap.pdf",
      "status": "bestanden",
      "sollfelder": 2,
      "abweichungen": 0,
      "fields": {
        "Neuer Dateiname": "ok",
        "Dokumenttyp": "ok"
      }
    },
    "mt-0009-audi-leasing-anderes-06-12-2019-pdf": {
      "datei": "Audi Leasing Anderes 06.12.2019.pdf",
      "status": "bestanden",
      "sollfelder": 5,
      "abweichungen": 0,
      "fields": {
        "Neuer Dateiname": "ok",
        "Lieferant": "ok",
        "Dokumenttyp": "ok",
        "Dokumentdatum": "ok",
        "KUNDENNR": "ok"
      }
    },
    "mt-0010-axa-versicherung-ag-information-29-08-2017-pdf": {
      "datei": "AXA Versicherung AG Information 29.08.2017.pdf",
      "status": "bestanden",
      "sollfelder": 5,
      "abweichungen": 0,
      "fields": {
        "Neuer Dateiname": "ok",
        "Lieferant": "ok",
        "Dokumenttyp": "ok",
        "Dokumentdatum": "ok",
        "VERSICHERUNGSNR": "ok"
      }
    },
    "mt-0011-bausparkasse-schw-bisch-hall-ag-anderes-28-11-20": {
      "datei": "Bausparkasse Schwäbisch Hall AG Anderes 28.11.2008.pdf",
      "status": "abweichung",
      "sollfelder": 4,
      "abweichungen": 1,
      "fields": {
        "Neuer Dateiname": "ok",
        "Lieferant": "ok",
        "Dokumenttyp": "abweichung",
        "Dokumentdatum": "ok"
      }
    },
    "mt-0012-bausparkasse-schw-bisch-hall-ag-information-01-1": {
      "datei": "Bausparkasse Schwäbisch Hall AG Information 01.12.2019.pdf",
      "status": "abweichung",
      "sollfelder": 5,
      "abweichungen": 4,
      "fields": {
        "Neuer Dateiname": "abweichung",
        "Lieferant": "abweichung",
        "Dokumenttyp": "abweichung",
        "Dokumentdatum": "ok",
        "VERSICHERUNGSNR": "abweichung"
      }
    },
    "mt-0013-bausparkasse-schw-bisch-hall-ag-information-05-0": {
      "datei": "Bausparkasse Schwäbisch Hall AG Information 05.02.2020.pdf",
      "status": "abweichung",
      "sollfelder": 4,
      "abweichungen": 3,
      "fields": {
        "Neuer Dateiname": "abweichung",
        "Lieferant": "abweichung",
        "Dokumenttyp": "abweichung",
        "Dokumentdatum": "ok"
      }
    },
    "mt-0014-bcsit-gmbh-information-pdf": {
      "datei": "BCSIT GmbH Information.pdf",
      "status": "bestanden",
      "sollfelder": 3,
      "abweichungen": 0,
      "fields": {
        "Neuer Dateiname": "ok",
        "Lieferant": "ok",
        "Dokumenttyp": "ok"
      }
    },
    "mt-0015-bongardstr-31-information-20-02-2025-pdf": {
      "datei": "Bongardstr. 31 Information 20.02.2025.pdf",
      "status": "abweichung",
      "sollfelder": 5,
      "abweichungen": 4,
      "fields": {
        "Neuer Dateiname": "abweichung",
        "Lieferant": "abweichung",
        "Dokumenttyp": "abweichung",
        "Dokumentdatum": "ok",
        "GESAMTBETRAG": "abweichung"
      }
    },
    "mt-0016-bongardstrabe-25-information-07-10-2021-pdf": {
      "datei": "BongardstraBe 25 Information 07.10.2021.pdf",
      "status": "abweichung",
      "sollfelder": 4,
      "abweichungen": 1,
      "fields": {
        "Neuer Dateiname": "ok",
        "Lieferant": "ok",
        "Dokumenttyp": "abweichung",
        "Dokumentdatum": "ok"
      }
    },
    "mt-0017-bonpdx-handelagm-mbh-rechnung-23-08-2025-pdf": {
      "datei": "bonpdx Handelagm. mbH Rechnung 23.08.2025.pdf",
      "status": "abweichung",
      "sollfelder": 7,
      "abweichungen": 3,
      "fields": {
        "Neuer Dateiname": "abweichung",
        "Lieferant": "ok",
        "Dokumenttyp": "ok",
        "Dokumentdatum": "ok",
        "RECHNR": "abweichung",
        "KUNDENNR": "abweichung",
        "GESAMTBETRAG": "ok"
      }
    },
    "mt-0018-bonprix-handeisges-rechnung-23-08-2025-pdf": {
      "datei": "bonprix Handeisges Rechnung 23.08.2025.pdf",
      "status": "abweichung",
      "sollfelder": 7,
      "abweichungen": 3,
      "fields": {
        "Neuer Dateiname": "abweichung",
        "Lieferant": "ok",
        "Dokumenttyp": "ok",
        "Dokumentdatum": "ok",
        "RECHNR": "abweichung",
        "KUNDENNR": "abweichung",
        "GESAMTBETRAG": "ok"
      }
    },
    "mt-0019-bonprix-handelsges-mbh-rechnung-02-07-2025-pdf": {
      "datei": "bonprix Handelsges. mbH Rechnung 02.07.2025.pdf",
      "status": "abweichung",
      "sollfelder": 7,
      "abweichungen": 3,
      "fields": {
        "Neuer Dateiname": "abweichung",
        "Lieferant": "ok",
        "Dokumenttyp": "ok",
        "Dokumentdatum": "ok",
        "RECHNR": "abweichung",
        "KUNDENNR": "abweichung",
        "GESAMTBETRAG": "ok"
      }
    },
    "mt-0020-bonprix-handelsges-mbh-rechnung-05-07-2025-2-pdf": {
      "datei": "bonprix Handelsges. mbH Rechnung 05.07.2025 (2) .pdf",
      "status": "abweichung",
      "sollfelder": 7,
      "abweichungen": 3,
      "fields": {
        "Neuer Dateiname": "abweichung",
        "Lieferant": "ok",
        "Dokumenttyp": "ok",
        "Dokumentdatum": "ok",
        "RECHNR": "abweichung",
        "KUNDENNR": "abweichung",
        "GESAMTBETRAG": "ok"
      }
    },
    "mt-0021-bonprix-handelsges-mbh-rechnung-05-07-2025-pdf": {
      "datei": "bonprix Handelsges. mbH Rechnung 05.07.2025.pdf",
      "status": "abweichung",
      "sollfelder": 7,
      "abweichungen": 3,
      "fields": {
        "Neuer Dateiname": "abweichung",
        "Lieferant": "ok",
        "Dokumenttyp": "ok",
        "Dokumentdatum": "ok",
        "RECHNR": "abweichung",
        "KUNDENNR": "abweichung",
        "GESAMTBETRAG": "ok"
      }
    },
    "mt-0022-bonprix-handelsges-mbh-rechnung-30-11-2024-pdf": {
      "datei": "bonprix Handelsges. mbH Rechnung 30.11.2024.pdf",
      "status": "abweichung",
      "sollfelder": 7,
      "abweichungen": 3,
      "fields": {
        "Neuer Dateiname": "abweichung",
        "Lieferant": "ok",
        "Dokumenttyp": "ok",
        "Dokumentdatum": "ok",
        "RECHNR": "abweichung",
        "KUNDENNR": "abweichung",
        "GESAMTBETRAG": "ok"
      }
    },
    "mt-0023-bonprix-handelsgesellschaft-mbh-rechnung-13-05-2": {
      "datei": "bonprix Handelsgesellschaft mbH Rechnung 13.05.2025.pdf",
      "status": "abweichung",
      "sollfelder": 7,
      "abweichungen": 3,
      "fields": {
        "Neuer Dateiname": "abweichung",
        "Lieferant": "ok",
        "Dokumenttyp": "ok",
        "Dokumentdatum": "ok",
        "RECHNR": "abweichung",
        "KUNDENNR": "abweichung",
        "GESAMTBETRAG": "ok"
      }
    },
    "mt-0024-brn94ddf8539961-000810-pdf": {
      "datei": "BRN94DDF8539961_000810.pdf",
      "status": "abweichung",
      "sollfelder": 3,
      "abweichungen": 3,
      "fields": {
        "Neuer Dateiname": "abweichung",
        "Lieferant": "abweichung",
        "Dokumenttyp": "abweichung"
      }
    },
    "mt-0025-b-romarkt-b-ttcher-ag-rechnung-17-07-2024-pdf": {
      "datei": "Büromarkt Böttcher AG Rechnung 17.07.2024.pdf",
      "status": "abweichung",
      "sollfelder": 8,
      "abweichungen": 3,
      "fields": {
        "Neuer Dateiname": "ok",
        "Lieferant": "ok",
        "Dokumenttyp": "ok",
        "Dokumentdatum": "ok",
        "RECHNR": "abweichung",
        "KUNDENNR": "abweichung",
        "AUFTRAGNR": "abweichung",
        "GESAMTBETRAG": "ok"
      }
    },
    "mt-0026-d-ul-rechnung-04-03-2024-pdf": {
      "datei": "D ul Rechnung 04.03.2024.pdf",
      "status": "abweichung",
      "sollfelder": 6,
      "abweichungen": 2,
      "fields": {
        "Neuer Dateiname": "abweichung",
        "Lieferant": "abweichung",
        "Dokumenttyp": "ok",
        "Dokumentdatum": "ok",
        "RECHNR": "ok",
        "GESAMTBETRAG": "ok"
      }
    },
    "mt-0027-debeka-allgemeine-versicherung-ag-anderes-20-04-": {
      "datei": "Debeka Allgemeine Versicherung AG Anderes 20.04.2026.pdf",
      "status": "bestanden",
      "sollfelder": 4,
      "abweichungen": 0,
      "fields": {
        "Neuer Dateiname": "ok",
        "Lieferant": "ok",
        "Dokumenttyp": "ok",
        "Dokumentdatum": "ok"
      }
    },
    "mt-0028-der-oberb-rgermeister-anderes-09-07-2018-pdf": {
      "datei": "Der Oberbürgermeister Anderes 09.07.2018.pdf",
      "status": "abweichung",
      "sollfelder": 6,
      "abweichungen": 2,
      "fields": {
        "Neuer Dateiname": "ok",
        "Lieferant": "ok",
        "Dokumenttyp": "abweichung",
        "Dokumentdatum": "ok",
        "RECHNR": "ok",
        "AKTENZEICHEN": "abweichung"
      }
    },
    "mt-0029-deutsche-post-ag-information-09-03-2020-pdf": {
      "datei": "Deutsche Post AG Information 09.03.2020.pdf",
      "status": "abweichung",
      "sollfelder": 4,
      "abweichungen": 1,
      "fields": {
        "Neuer Dateiname": "ok",
        "Lieferant": "ok",
        "Dokumenttyp": "abweichung",
        "Dokumentdatum": "ok"
      }
    },
    "mt-0030-deutsche-post-ag-vertrag-10-10-2022-pdf": {
      "datei": "Deutsche Post AG Vertrag 10.10.2022.pdf",
      "status": "abweichung",
      "sollfelder": 5,
      "abweichungen": 3,
      "fields": {
        "Neuer Dateiname": "abweichung",
        "Lieferant": "ok",
        "Dokumenttyp": "abweichung",
        "Dokumentdatum": "ok",
        "AKTENZEICHEN": "abweichung"
      }
    },
    "mt-0031-dhl-paket-gmbh-anderes-14-10-2024-pdf": {
      "datei": "DHL Paket GmbH Anderes 14.10.2024.pdf",
      "status": "abweichung",
      "sollfelder": 6,
      "abweichungen": 1,
      "fields": {
        "Neuer Dateiname": "ok",
        "Lieferant": "ok",
        "Dokumenttyp": "abweichung",
        "Dokumentdatum": "ok",
        "KUNDENNR": "ok",
        "GESAMTBETRAG": "ok"
      }
    },
    "mt-0032-die-smarte-werkstatt-kassenzettel-04-04-2025-pdf": {
      "datei": "die smarte werkstatt Kassenzettel 04.04.2025.pdf",
      "status": "abweichung",
      "sollfelder": 7,
      "abweichungen": 1,
      "fields": {
        "Neuer Dateiname": "ok",
        "Lieferant": "ok",
        "Dokumenttyp": "ok",
        "Dokumentdatum": "ok",
        "RECHNR": "ok",
        "KUNDENNR": "ok",
        "GESAMTBETRAG": "abweichung"
      }
    },
    "mt-0033-die-smarte-werkstatt-rechnung-02-04-2026-pdf": {
      "datei": "die smarte werkstatt Rechnung 02.04.2026.pdf",
      "status": "abweichung",
      "sollfelder": 7,
      "abweichungen": 1,
      "fields": {
        "Neuer Dateiname": "ok",
        "Lieferant": "ok",
        "Dokumenttyp": "ok",
        "Dokumentdatum": "ok",
        "RECHNR": "ok",
        "KUNDENNR": "ok",
        "GESAMTBETRAG": "abweichung"
      }
    },
    "mt-0034-die-smarte-werkstatt-rechnung-20-11-2025-pdf": {
      "datei": "die smarte werkstatt Rechnung 20.11.2025.pdf",
      "status": "bestanden",
      "sollfelder": 7,
      "abweichungen": 0,
      "fields": {
        "Neuer Dateiname": "ok",
        "Lieferant": "ok",
        "Dokumenttyp": "ok",
        "Dokumentdatum": "ok",
        "RECHNR": "ok",
        "KUNDENNR": "ok",
        "GESAMTBETRAG": "ok"
      }
    },
    "mt-0035-dkv-deutsche-krankenversicherung-ag-information-": {
      "datei": "DKV Deutsche Krankenversicherung AG Information 16.02.2026.pdf",
      "status": "abweichung",
      "sollfelder": 4,
      "abweichungen": 3,
      "fields": {
        "Neuer Dateiname": "abweichung",
        "Lieferant": "abweichung",
        "Dokumenttyp": "abweichung",
        "Dokumentdatum": "ok"
      }
    },
    "mt-0036-dr-med-fahim-ayami-rechnung-06-05-2026-pdf": {
      "datei": "Dr. med. Fahim Ayami Rechnung 06.05.2026.pdf",
      "status": "abweichung",
      "sollfelder": 6,
      "abweichungen": 4,
      "fields": {
        "Neuer Dateiname": "abweichung",
        "Lieferant": "abweichung",
        "Dokumenttyp": "ok",
        "Dokumentdatum": "ok",
        "RECHNR": "abweichung",
        "GESAMTBETRAG": "abweichung"
      }
    },
    "mt-0037-dr-med-dent-axel-rechnung-15-04-2026-pdf": {
      "datei": "Dr. med.dent.Axel Rechnung 15.04.2026.pdf",
      "status": "abweichung",
      "sollfelder": 6,
      "abweichungen": 5,
      "fields": {
        "Neuer Dateiname": "abweichung",
        "Lieferant": "abweichung",
        "Dokumenttyp": "ok",
        "Dokumentdatum": "abweichung",
        "RECHNR": "abweichung",
        "GESAMTBETRAG": "abweichung"
      }
    },
    "mt-0038-dr-med-dent-axel-rechnung-26-08-2025-pdf": {
      "datei": "Dr. med.dent.Axel Rechnung 26.08.2025.pdf",
      "status": "abweichung",
      "sollfelder": 6,
      "abweichungen": 5,
      "fields": {
        "Neuer Dateiname": "abweichung",
        "Lieferant": "abweichung",
        "Dokumenttyp": "ok",
        "Dokumentdatum": "abweichung",
        "RECHNR": "abweichung",
        "GESAMTBETRAG": "abweichung"
      }
    },
    "mt-0039-edeka-foodservice-stiftung-co-kg-beleg-13-05-209": {
      "datei": "Edeka Foodservice Stiftung _ Co. KG Beleg 13.05.2096.pdf",
      "status": "bestanden",
      "sollfelder": 5,
      "abweichungen": 0,
      "fields": {
        "Neuer Dateiname": "ok",
        "Lieferant": "ok",
        "Dokumenttyp": "ok",
        "Dokumentdatum": "ok",
        "GESAMTBETRAG": "ok"
      }
    },
    "mt-0040-edeka-foodservice-stiftung-co-kg-kassenzettel-26": {
      "datei": "Edeka Foodservice Stiftung _ Co. KG Kassenzettel 26.06.25.pdf",
      "status": "bestanden",
      "sollfelder": 7,
      "abweichungen": 0,
      "fields": {
        "Neuer Dateiname": "ok",
        "Lieferant": "ok",
        "Dokumenttyp": "ok",
        "Dokumentdatum": "ok",
        "RECHNR": "ok",
        "KUNDENNR": "ok",
        "GESAMTBETRAG": "ok"
      }
    },
    "mt-0041-eheleute-heinz-georg-und-information-18-08-2020-": {
      "datei": "Eheleute Heinz-Georg und Information 18.08.2020.pdf",
      "status": "abweichung",
      "sollfelder": 5,
      "abweichungen": 2,
      "fields": {
        "Neuer Dateiname": "ok",
        "Lieferant": "ok",
        "Dokumenttyp": "abweichung",
        "Dokumentdatum": "ok",
        "AKTENZEICHEN": "abweichung"
      }
    },
    "mt-0042-elliot-gmbh-rechnung-20-11-2025-pdf": {
      "datei": "Elliot GmbH Rechnung 20.11.2025.pdf",
      "status": "abweichung",
      "sollfelder": 7,
      "abweichungen": 1,
      "fields": {
        "Neuer Dateiname": "ok",
        "Lieferant": "ok",
        "Dokumenttyp": "ok",
        "Dokumentdatum": "ok",
        "RECHNR": "ok",
        "AUFTRAGNR": "ok",
        "GESAMTBETRAG": "abweichung"
      }
    },
    "mt-0043-flascheral-norge-sch-kassenzettel-pdf": {
      "datei": "Flascheral Norge sch Kassenzettel.pdf",
      "status": "abweichung",
      "sollfelder": 4,
      "abweichungen": 3,
      "fields": {
        "Neuer Dateiname": "abweichung",
        "Lieferant": "abweichung",
        "Dokumenttyp": "ok",
        "GESAMTBETRAG": "abweichung"
      }
    },
    "mt-0044-franke-gmbh-co-kg-anderes-04-02-2024-pdf": {
      "datei": "Franke GmbH _ Co. KG Anderes 04.02.2024.pdf",
      "status": "abweichung",
      "sollfelder": 7,
      "abweichungen": 5,
      "fields": {
        "Neuer Dateiname": "abweichung",
        "Lieferant": "abweichung",
        "Dokumenttyp": "abweichung",
        "Dokumentdatum": "ok",
        "RECHNR": "abweichung",
        "KUNDENNR": "abweichung",
        "GESAMTBETRAG": "ok"
      }
    },
    "mt-0045-franke-gmbh-co-kg-anderes-23-07-2023-pdf": {
      "datei": "Franke GmbH _ Co. KG Anderes 23.07.2023.pdf",
      "status": "abweichung",
      "sollfelder": 7,
      "abweichungen": 5,
      "fields": {
        "Neuer Dateiname": "abweichung",
        "Lieferant": "abweichung",
        "Dokumenttyp": "abweichung",
        "Dokumentdatum": "ok",
        "RECHNR": "abweichung",
        "KUNDENNR": "abweichung",
        "GESAMTBETRAG": "ok"
      }
    },
    "mt-0046-franke-gmbh-co-kg-kassenzettel-15-02-2026-pdf": {
      "datei": "Franke GmbH _ Co. KG Kassenzettel 15.02.2026.pdf",
      "status": "abweichung",
      "sollfelder": 7,
      "abweichungen": 5,
      "fields": {
        "Neuer Dateiname": "abweichung",
        "Lieferant": "abweichung",
        "Dokumenttyp": "abweichung",
        "Dokumentdatum": "ok",
        "RECHNR": "abweichung",
        "KUNDENNR": "abweichung",
        "GESAMTBETRAG": "ok"
      }
    },
    "mt-0047-franke-gmbh-co-kg-rechnung-16-02-2025-pdf": {
      "datei": "Franke GmbH _ Co. KG Rechnung 16.02.2025.pdf",
      "status": "abweichung",
      "sollfelder": 7,
      "abweichungen": 5,
      "fields": {
        "Neuer Dateiname": "abweichung",
        "Lieferant": "abweichung",
        "Dokumenttyp": "abweichung",
        "Dokumentdatum": "ok",
        "RECHNR": "abweichung",
        "KUNDENNR": "abweichung",
        "GESAMTBETRAG": "ok"
      }
    },
    "mt-0048-franke-gmbh-co-kg-rechnung-20-07-2025-pdf": {
      "datei": "Franke GmbH _ Co. KG Rechnung 20.07.2025.pdf",
      "status": "abweichung",
      "sollfelder": 7,
      "abweichungen": 3,
      "fields": {
        "Neuer Dateiname": "abweichung",
        "Lieferant": "abweichung",
        "Dokumenttyp": "ok",
        "Dokumentdatum": "ok",
        "RECHNR": "ok",
        "KUNDENNR": "abweichung",
        "GESAMTBETRAG": "ok"
      }
    },
    "mt-0049-friedemann-ahlmeyer-kassenzettel-15-05-25-pdf": {
      "datei": "Friedemann Ahlmeyer Kassenzettel 15.05.25.pdf",
      "status": "abweichung",
      "sollfelder": 6,
      "abweichungen": 1,
      "fields": {
        "Neuer Dateiname": "ok",
        "Lieferant": "ok",
        "Dokumenttyp": "ok",
        "Dokumentdatum": "ok",
        "RECHNR": "ok",
        "GESAMTBETRAG": "abweichung"
      }
    },
    "mt-0050-funke-medien-nrw-gmbh-information-15-02-2016-2-p": {
      "datei": "FUNKE MEDIEN NRW GmbH Information 15.02.2016 (2) .pdf",
      "status": "bestanden",
      "sollfelder": 6,
      "abweichungen": 0,
      "fields": {
        "Neuer Dateiname": "ok",
        "Lieferant": "ok",
        "Dokumenttyp": "ok",
        "Dokumentdatum": "ok",
        "RECHNR": "ok",
        "KUNDENNR": "ok"
      }
    },
    "mt-0051-funke-medien-nrw-gmbh-information-15-02-2016-pdf": {
      "datei": "FUNKE MEDIEN NRW GmbH Information 15.02.2016.pdf",
      "status": "bestanden",
      "sollfelder": 6,
      "abweichungen": 0,
      "fields": {
        "Neuer Dateiname": "ok",
        "Lieferant": "ok",
        "Dokumenttyp": "ok",
        "Dokumentdatum": "ok",
        "RECHNR": "ok",
        "KUNDENNR": "ok"
      }
    },
    "mt-0052-gebers-kassenzettel-18-07-2025-pdf": {
      "datei": "Gebers Kassenzettel 18.07.2025.pdf",
      "status": "abweichung",
      "sollfelder": 6,
      "abweichungen": 3,
      "fields": {
        "Neuer Dateiname": "abweichung",
        "Lieferant": "abweichung",
        "Dokumenttyp": "ok",
        "Dokumentdatum": "ok",
        "RECHNR": "abweichung",
        "GESAMTBETRAG": "ok"
      }
    },
    "mt-0053-hagebau-partner-card-service-anderes-03-04-2022-": {
      "datei": "hagebau Partner-Card Service Anderes 03.04.2022.pdf",
      "status": "abweichung",
      "sollfelder": 4,
      "abweichungen": 1,
      "fields": {
        "Neuer Dateiname": "ok",
        "Lieferant": "ok",
        "Dokumenttyp": "abweichung",
        "Dokumentdatum": "ok"
      }
    },
    "mt-0054-hanse-merkur-information-30-06-2025-pdf": {
      "datei": "Hanse Merkur Information 30.06.2025.pdf",
      "status": "abweichung",
      "sollfelder": 5,
      "abweichungen": 4,
      "fields": {
        "Neuer Dateiname": "abweichung",
        "Lieferant": "ok",
        "Dokumenttyp": "abweichung",
        "Dokumentdatum": "abweichung",
        "VERSICHERUNGSNR": "abweichung"
      }
    },
    "mt-0055-hansemerkur-speziale-krankenversicherung-ag-info": {
      "datei": "HanseMerkur Speziale Krankenversicherung AG Information 30.03.2021.pdf",
      "status": "abweichung",
      "sollfelder": 5,
      "abweichungen": 4,
      "fields": {
        "Neuer Dateiname": "abweichung",
        "Lieferant": "abweichung",
        "Dokumenttyp": "abweichung",
        "Dokumentdatum": "ok",
        "VERSICHERUNGSNR": "abweichung"
      }
    },
    "mt-0056-happysize-anderes-21-08-2023-pdf": {
      "datei": "HAPPYsize Anderes 21.08.2023.pdf",
      "status": "abweichung",
      "sollfelder": 7,
      "abweichungen": 3,
      "fields": {
        "Neuer Dateiname": "abweichung",
        "Lieferant": "abweichung",
        "Dokumenttyp": "abweichung",
        "Dokumentdatum": "ok",
        "RECHNR": "ok",
        "KUNDENNR": "ok",
        "GESAMTBETRAG": "ok"
      }
    },
    "mt-0057-haufe-service-center-gmbh-rechnung-14-05-25-pdf": {
      "datei": "Haufe Service Center GmbH Rechnung 14.05.25.pdf",
      "status": "abweichung",
      "sollfelder": 8,
      "abweichungen": 3,
      "fields": {
        "Neuer Dateiname": "abweichung",
        "Lieferant": "ok",
        "Dokumenttyp": "ok",
        "Dokumentdatum": "ok",
        "RECHNR": "abweichung",
        "KUNDENNR": "abweichung",
        "AUFTRAGNR": "ok",
        "GESAMTBETRAG": "ok"
      }
    },
    "mt-0058-hauplzollamt-dortmund-anderes-13-01-2022-pdf": {
      "datei": "Hauplzollamt Dortmund Anderes 13.01.2022.pdf",
      "status": "abweichung",
      "sollfelder": 8,
      "abweichungen": 3,
      "fields": {
        "Neuer Dateiname": "ok",
        "Lieferant": "ok",
        "Dokumenttyp": "ok",
        "Dokumentdatum": "ok",
        "RECHNR": "ok",
        "AKTENZEICHEN": "abweichung",
        "VERSICHERUNGSNR": "abweichung",
        "GESAMTBETRAG": "abweichung"
      }
    },
    "mt-0059-hauptaofamt-dortmund-anderes-13-12-2022-pdf": {
      "datei": "Hauptaofamt Dortmund Anderes 13.12.2022.pdf",
      "status": "abweichung",
      "sollfelder": 8,
      "abweichungen": 1,
      "fields": {
        "Neuer Dateiname": "ok",
        "Lieferant": "ok",
        "Dokumenttyp": "ok",
        "Dokumentdatum": "ok",
        "RECHNR": "ok",
        "AKTENZEICHEN": "abweichung",
        "VERSICHERUNGSNR": "ok",
        "GESAMTBETRAG": "ok"
      }
    },
    "mt-0060-hauptzollamt-dortmund-anderes-07-02-2019-pdf": {
      "datei": "Hauptzollamt Dortmund Anderes 07.02.2019.pdf",
      "status": "abweichung",
      "sollfelder": 8,
      "abweichungen": 3,
      "fields": {
        "Neuer Dateiname": "ok",
        "Lieferant": "ok",
        "Dokumenttyp": "ok",
        "Dokumentdatum": "ok",
        "RECHNR": "ok",
        "AKTENZEICHEN": "abweichung",
        "VERSICHERUNGSNR": "abweichung",
        "GESAMTBETRAG": "abweichung"
      }
    },
    "mt-0061-hauptzollamt-dortmund-anderes-16-12-2022-pdf": {
      "datei": "Hauptzollamt Dortmund Anderes 16.12.2022.pdf",
      "status": "abweichung",
      "sollfelder": 8,
      "abweichungen": 1,
      "fields": {
        "Neuer Dateiname": "ok",
        "Lieferant": "ok",
        "Dokumenttyp": "ok",
        "Dokumentdatum": "ok",
        "RECHNR": "ok",
        "AKTENZEICHEN": "abweichung",
        "VERSICHERUNGSNR": "ok",
        "GESAMTBETRAG": "ok"
      }
    },
    "mt-0062-hauptzollamt-dortmund-anderes-27-10-2018-pdf": {
      "datei": "Hauptzollamt Dortmund Anderes 27.10.2018.pdf",
      "status": "abweichung",
      "sollfelder": 8,
      "abweichungen": 2,
      "fields": {
        "Neuer Dateiname": "ok",
        "Lieferant": "ok",
        "Dokumenttyp": "ok",
        "Dokumentdatum": "ok",
        "RECHNR": "ok",
        "AKTENZEICHEN": "abweichung",
        "VERSICHERUNGSNR": "ok",
        "GESAMTBETRAG": "abweichung"
      }
    },
    "mt-0063-heinz-georg-hepp-information-02-06-2019-pdf": {
      "datei": "Heinz-Georg Hepp Information 02.06.2019.pdf",
      "status": "bestanden",
      "sollfelder": 4,
      "abweichungen": 0,
      "fields": {
        "Neuer Dateiname": "ok",
        "Lieferant": "ok",
        "Dokumenttyp": "ok",
        "Dokumentdatum": "ok"
      }
    },
    "mt-0064-heinz-georg-hepp-information-24-04-2026-pdf": {
      "datei": "Heinz-Georg Hepp Information 24.04.2026.pdf",
      "status": "bestanden",
      "sollfelder": 4,
      "abweichungen": 0,
      "fields": {
        "Neuer Dateiname": "ok",
        "Lieferant": "ok",
        "Dokumenttyp": "ok",
        "Dokumentdatum": "ok"
      }
    },
    "mt-0065-heinz-georg-hepp-kassenzettel-pdf": {
      "datei": "Heinz-Georg Hepp Kassenzettel.pdf",
      "status": "bestanden",
      "sollfelder": 3,
      "abweichungen": 0,
      "fields": {
        "Neuer Dateiname": "ok",
        "Lieferant": "ok",
        "Dokumenttyp": "ok"
      }
    },
    "mt-0066-heinz-georg-hepp-rechnung-17-09-2025-pdf": {
      "datei": "Heinz-Georg Hepp Rechnung 17.09.2025.pdf",
      "status": "bestanden",
      "sollfelder": 6,
      "abweichungen": 0,
      "fields": {
        "Neuer Dateiname": "ok",
        "Lieferant": "ok",
        "Dokumenttyp": "ok",
        "Dokumentdatum": "ok",
        "RECHNR": "ok",
        "GESAMTBETRAG": "ok"
      }
    },
    "mt-0067-heinz-georg-hepp-rechnung-23-08-2025-pdf": {
      "datei": "Heinz-Georg Hepp Rechnung 23.08.2025.pdf",
      "status": "abweichung",
      "sollfelder": 7,
      "abweichungen": 4,
      "fields": {
        "Neuer Dateiname": "abweichung",
        "Lieferant": "abweichung",
        "Dokumenttyp": "ok",
        "Dokumentdatum": "ok",
        "RECHNR": "abweichung",
        "BESTELLNR": "ok",
        "GESAMTBETRAG": "abweichung"
      }
    },
    "mt-0068-heinz-georg-hepp-rechnung-27-04-2026-pdf": {
      "datei": "Heinz-Georg Hepp Rechnung 27.04.2026.pdf",
      "status": "bestanden",
      "sollfelder": 6,
      "abweichungen": 0,
      "fields": {
        "Neuer Dateiname": "ok",
        "Lieferant": "ok",
        "Dokumenttyp": "ok",
        "Dokumentdatum": "ok",
        "RECHNR": "ok",
        "GESAMTBETRAG": "ok"
      }
    },
    "mt-0069-hepp-simone-information-14-09-2017-pdf": {
      "datei": "Hepp, Simone Information 14.09.2017.pdf",
      "status": "abweichung",
      "sollfelder": 4,
      "abweichungen": 4,
      "fields": {
        "Neuer Dateiname": "abweichung",
        "Lieferant": "abweichung",
        "Dokumenttyp": "abweichung",
        "Dokumentdatum": "abweichung"
      }
    },
    "mt-0070-information-31-07-2021-pdf": {
      "datei": "Information 31.07.2021.pdf",
      "status": "bestanden",
      "sollfelder": 3,
      "abweichungen": 0,
      "fields": {
        "Neuer Dateiname": "ok",
        "Dokumenttyp": "ok",
        "Dokumentdatum": "ok"
      }
    },
    "mt-0071-johannes-gerstaecker-verlag-gmbh-co-kg-anderes-2": {
      "datei": "Johannes Gerstaecker Verlag GmbH _ Co. KG Anderes 28.07.2025.pdf",
      "status": "bestanden",
      "sollfelder": 6,
      "abweichungen": 0,
      "fields": {
        "Neuer Dateiname": "ok",
        "Lieferant": "ok",
        "Dokumenttyp": "ok",
        "Dokumentdatum": "ok",
        "KUNDENNR": "ok",
        "LIEFERSCHEINNR": "ok"
      }
    },
    "mt-0072-kassenzettel-14-05-25-pdf": {
      "datei": "Kassenzettel 14.05.25.pdf",
      "status": "bestanden",
      "sollfelder": 4,
      "abweichungen": 0,
      "fields": {
        "Neuer Dateiname": "ok",
        "Lieferant": "ok",
        "Dokumenttyp": "ok",
        "GESAMTBETRAG": "ok"
      }
    },
    "mt-0073-kend-anderes-20-04-2026-pdf": {
      "datei": "Kend Anderes 20.04.2026.pdf",
      "status": "bestanden",
      "sollfelder": 5,
      "abweichungen": 0,
      "fields": {
        "Neuer Dateiname": "ok",
        "Lieferant": "ok",
        "Dokumenttyp": "ok",
        "Dokumentdatum": "ok",
        "BESTELLNR": "ok"
      }
    },
    "mt-0074-kfw-anderes-26-12-2018-pdf": {
      "datei": "KfW Anderes 26.12.2018.pdf",
      "status": "bestanden",
      "sollfelder": 4,
      "abweichungen": 0,
      "fields": {
        "Neuer Dateiname": "ok",
        "Lieferant": "ok",
        "Dokumenttyp": "ok",
        "Dokumentdatum": "ok"
      }
    },
    "mt-0075-kfw-information-03-04-2017-pdf": {
      "datei": "KfW Information 03.04.2017.pdf",
      "status": "bestanden",
      "sollfelder": 4,
      "abweichungen": 0,
      "fields": {
        "Neuer Dateiname": "ok",
        "Lieferant": "ok",
        "Dokumenttyp": "ok",
        "Dokumentdatum": "ok"
      }
    },
    "mt-0076-kraftfahrt-bundesamt-information-14-09-2016-pdf": {
      "datei": "Kraftfahrt-Bundesamt Information 14.09.2016.pdf",
      "status": "abweichung",
      "sollfelder": 4,
      "abweichungen": 3,
      "fields": {
        "Neuer Dateiname": "abweichung",
        "Lieferant": "abweichung",
        "Dokumenttyp": "abweichung",
        "Dokumentdatum": "ok"
      }
    },
    "mt-0077-kraftfahrt-bundesamt-information-21-09-2016-pdf": {
      "datei": "Kraftfahrt-Bundesamt Information 21.09.2016.pdf",
      "status": "abweichung",
      "sollfelder": 4,
      "abweichungen": 3,
      "fields": {
        "Neuer Dateiname": "abweichung",
        "Lieferant": "abweichung",
        "Dokumenttyp": "abweichung",
        "Dokumentdatum": "ok"
      }
    },
    "mt-0078-labor-f-r-klinische-diagnostik-gmbh-co-kg-rechnu": {
      "datei": "LABOR FÜR KLINISCHE DIAGNOSTIK GMBH _ CO. KG Rechnung 24.04.2026.pdf",
      "status": "bestanden",
      "sollfelder": 7,
      "abweichungen": 0,
      "fields": {
        "Neuer Dateiname": "ok",
        "Lieferant": "ok",
        "Dokumenttyp": "ok",
        "Dokumentdatum": "ok",
        "RECHNR": "ok",
        "KUNDENNR": "ok",
        "GESAMTBETRAG": "ok"
      }
    },
    "mt-0079-lehner-und-kollegen-rechnung-03-07-2025-pdf": {
      "datei": "Lehner und Kollegen Rechnung 03.07.2025.pdf",
      "status": "abweichung",
      "sollfelder": 5,
      "abweichungen": 2,
      "fields": {
        "Neuer Dateiname": "abweichung",
        "Lieferant": "abweichung",
        "Dokumenttyp": "ok",
        "Dokumentdatum": "ok",
        "GESAMTBETRAG": "ok"
      }
    },
    "mt-0080-lehner-und-kollegen-rechnung-12-02-2025-pdf": {
      "datei": "Lehner und Kollegen Rechnung 12.02.2025.pdf",
      "status": "abweichung",
      "sollfelder": 7,
      "abweichungen": 4,
      "fields": {
        "Neuer Dateiname": "abweichung",
        "Lieferant": "abweichung",
        "Dokumenttyp": "ok",
        "Dokumentdatum": "ok",
        "RECHNR": "abweichung",
        "AKTENZEICHEN": "abweichung",
        "GESAMTBETRAG": "ok"
      }
    },
    "mt-0081-leones-rechtsanw-lte-information-20-08-2021-pdf": {
      "datei": "LEONES Rechtsanwälte Information 20.08.2021.pdf",
      "status": "abweichung",
      "sollfelder": 4,
      "abweichungen": 1,
      "fields": {
        "Neuer Dateiname": "ok",
        "Lieferant": "ok",
        "Dokumenttyp": "abweichung",
        "Dokumentdatum": "ok"
      }
    },
    "mt-0082-lidl-digital-deutschland-gmbh-co-kg-rechnung-19-": {
      "datei": "Lidl Digital Deutschland GmbH _ Co. KG Rechnung 19.10.2025.pdf",
      "status": "abweichung",
      "sollfelder": 8,
      "abweichungen": 5,
      "fields": {
        "Neuer Dateiname": "abweichung",
        "Lieferant": "ok",
        "Dokumenttyp": "ok",
        "Dokumentdatum": "ok",
        "RECHNR": "abweichung",
        "KUNDENNR": "abweichung",
        "BESTELLNR": "abweichung",
        "GESAMTBETRAG": "abweichung"
      }
    },
    "mt-0083-lieferadresse-anderes-23-03-2025-pdf": {
      "datei": "Lieferadresse Anderes 23.03.2025.pdf",
      "status": "abweichung",
      "sollfelder": 5,
      "abweichungen": 2,
      "fields": {
        "Neuer Dateiname": "abweichung",
        "Lieferant": "abweichung",
        "Dokumenttyp": "ok",
        "Dokumentdatum": "ok",
        "BESTELLNR": "ok"
      }
    },
    "mt-0084-lieferadresse-rechnung-22-09-2025-pdf": {
      "datei": "Lieferadresse Rechnung 22.09.2025.pdf",
      "status": "bestanden",
      "sollfelder": 7,
      "abweichungen": 0,
      "fields": {
        "Neuer Dateiname": "ok",
        "Lieferant": "ok",
        "Dokumenttyp": "ok",
        "Dokumentdatum": "ok",
        "RECHNR": "ok",
        "KUNDENNR": "ok",
        "GESAMTBETRAG": "ok"
      }
    },
    "mt-0085-lieferadresse-rechnung-24-11-2023-pdf": {
      "datei": "Lieferadresse Rechnung 24.11.2023.pdf",
      "status": "abweichung",
      "sollfelder": 8,
      "abweichungen": 2,
      "fields": {
        "Neuer Dateiname": "ok",
        "Lieferant": "ok",
        "Dokumenttyp": "ok",
        "Dokumentdatum": "ok",
        "RECHNR": "ok",
        "BESTELLNR": "ok",
        "LIEFERSCHEINNR": "abweichung",
        "GESAMTBETRAG": "abweichung"
      }
    },
    "mt-0086-lowenstein-medical-anderes-07-11-2025-pdf": {
      "datei": "Lowenstein Medical Anderes 07.11.2025.pdf",
      "status": "abweichung",
      "sollfelder": 3,
      "abweichungen": 3,
      "fields": {
        "Neuer Dateiname": "abweichung",
        "Lieferant": "abweichung",
        "Dokumenttyp": "abweichung"
      }
    },
    "mt-0087-luttermann-gmbh-information-18-04-2024-pdf": {
      "datei": "Luttermann GmbH Information 18.04.2024.pdf",
      "status": "bestanden",
      "sollfelder": 4,
      "abweichungen": 0,
      "fields": {
        "Neuer Dateiname": "ok",
        "Lieferant": "ok",
        "Dokumenttyp": "ok",
        "Dokumentdatum": "ok"
      }
    },
    "mt-0088-lvm-versicherungen-anderes-02-03-2020-pdf": {
      "datei": "LVM Versicherungen Anderes 02.03.2020.pdf",
      "status": "bestanden",
      "sollfelder": 5,
      "abweichungen": 0,
      "fields": {
        "Neuer Dateiname": "ok",
        "Lieferant": "ok",
        "Dokumenttyp": "ok",
        "Dokumentdatum": "ok",
        "VERSICHERUNGSNR": "ok"
      }
    },
    "mt-0089-maximilian-hepp-anderes-14-10-1999-pdf": {
      "datei": "Maximilian Hepp Anderes 14.10.1999.pdf",
      "status": "bestanden",
      "sollfelder": 4,
      "abweichungen": 0,
      "fields": {
        "Neuer Dateiname": "ok",
        "Lieferant": "ok",
        "Dokumenttyp": "ok",
        "Dokumentdatum": "ok"
      }
    },
    "mt-0090-media-markt-tv-hifi-elektro-gmbh-bochum-kassenze": {
      "datei": "Media Markt TV-HiFi-Elektro GmbH Bochum Kassenzettel 30.03.2026.pdf",
      "status": "abweichung",
      "sollfelder": 7,
      "abweichungen": 1,
      "fields": {
        "Neuer Dateiname": "ok",
        "Lieferant": "ok",
        "Dokumenttyp": "ok",
        "Dokumentdatum": "ok",
        "RECHNR": "ok",
        "AUFTRAGNR": "ok",
        "GESAMTBETRAG": "abweichung"
      }
    },
    "mt-0091-name-vertrag-03-06-2019-pdf": {
      "datei": "Name Vertrag 03.06.2019.pdf",
      "status": "abweichung",
      "sollfelder": 5,
      "abweichungen": 3,
      "fields": {
        "Neuer Dateiname": "abweichung",
        "Lieferant": "abweichung",
        "Dokumenttyp": "ok",
        "Dokumentdatum": "ok",
        "GESAMTBETRAG": "abweichung"
      }
    },
    "mt-0092-nikolaos-rigas-vertrag-30-11-2021-pdf": {
      "datei": "Nikolaos Rigas Vertrag 30.11.2021.pdf",
      "status": "abweichung",
      "sollfelder": 4,
      "abweichungen": 1,
      "fields": {
        "Neuer Dateiname": "ok",
        "Lieferant": "ok",
        "Dokumenttyp": "abweichung",
        "Dokumentdatum": "ok"
      }
    },
    "mt-0093-polizeipr-sidium-information-01-05-2018-pdf": {
      "datei": "Polizeipräsidium Information 01.05.2018.pdf",
      "status": "abweichung",
      "sollfelder": 6,
      "abweichungen": 1,
      "fields": {
        "Neuer Dateiname": "ok",
        "Lieferant": "ok",
        "Dokumenttyp": "ok",
        "Dokumentdatum": "ok",
        "RECHNR": "ok",
        "AKTENZEICHEN": "abweichung"
      }
    },
    "mt-0094-polizeipr-sidium-information-01-05-2018-005-002-": {
      "datei": "Polizeipräsidium Information 01.05.2018_005_002.pdf",
      "status": "abweichung",
      "sollfelder": 6,
      "abweichungen": 1,
      "fields": {
        "Neuer Dateiname": "ok",
        "Lieferant": "ok",
        "Dokumenttyp": "ok",
        "Dokumentdatum": "ok",
        "RECHNR": "ok",
        "AKTENZEICHEN": "abweichung"
      }
    },
    "mt-0095-privatbrauerei-moritz-fiege-gmbh-co-kg-kassenzet": {
      "datei": "Privatbrauerei Moritz Fiege GmbH _ Co. KG Kassenzettel 16.05.25.pdf",
      "status": "bestanden",
      "sollfelder": 6,
      "abweichungen": 0,
      "fields": {
        "Neuer Dateiname": "ok",
        "Lieferant": "ok",
        "Dokumenttyp": "ok",
        "Dokumentdatum": "ok",
        "RECHNR": "ok",
        "GESAMTBETRAG": "ok"
      }
    },
    "mt-0096-ptlyslo-polnt-rechnung-28-03-2025-pdf": {
      "datei": "ptlyslo polnt Rechnung 28.03.2025.pdf",
      "status": "bestanden",
      "sollfelder": 6,
      "abweichungen": 0,
      "fields": {
        "Neuer Dateiname": "ok",
        "Lieferant": "ok",
        "Dokumenttyp": "ok",
        "Dokumentdatum": "ok",
        "RECHNR": "ok",
        "GESAMTBETRAG": "ok"
      }
    },
    "mt-0097-rathaus-bochum-anderes-04-01-2019-pdf": {
      "datei": "Rathaus Bochum Anderes 04.01.2019.pdf",
      "status": "abweichung",
      "sollfelder": 5,
      "abweichungen": 4,
      "fields": {
        "Neuer Dateiname": "abweichung",
        "Lieferant": "abweichung",
        "Dokumenttyp": "abweichung",
        "Dokumentdatum": "ok",
        "RECHNR": "abweichung"
      }
    },
    "mt-0098-reichelt-elektronik-gmbh-co-kg-rechnung-07-07-25": {
      "datei": "reichelt elektronik GmbH _ Co. KG Rechnung 07.07.25.pdf",
      "status": "abweichung",
      "sollfelder": 6,
      "abweichungen": 1,
      "fields": {
        "Neuer Dateiname": "ok",
        "Lieferant": "ok",
        "Dokumenttyp": "ok",
        "Dokumentdatum": "ok",
        "VERSICHERUNGSNR": "ok",
        "GESAMTBETRAG": "abweichung"
      }
    },
    "mt-0099-santander-consumer-bank-ag-rechnung-15-07-2022-p": {
      "datei": "Santander Consumer Bank AG Rechnung 15.07.2022.pdf",
      "status": "abweichung",
      "sollfelder": 8,
      "abweichungen": 4,
      "fields": {
        "Neuer Dateiname": "abweichung",
        "Lieferant": "abweichung",
        "Dokumenttyp": "abweichung",
        "Dokumentdatum": "ok",
        "RECHNR": "ok",
        "KUNDENNR": "ok",
        "VERSICHERUNGSNR": "ok",
        "GESAMTBETRAG": "abweichung"
      }
    },
    "mt-0100-schl-ssel-m-ller-tyesore-gmbh-anderes-07-10-2021": {
      "datei": "Schlüssel-Müller-TYesore GmbH Anderes 07.10.2021.pdf",
      "status": "bestanden",
      "sollfelder": 6,
      "abweichungen": 0,
      "fields": {
        "Neuer Dateiname": "ok",
        "Lieferant": "ok",
        "Dokumenttyp": "ok",
        "Dokumentdatum": "ok",
        "KUNDENNR": "ok",
        "BESTELLNR": "ok"
      }
    },
    "mt-0101-schwimmbadhandel-heike-meyer-rechnung-13-05-2026": {
      "datei": "Schwimmbadhandel Heike Meyer Rechnung 13.05.2026.pdf",
      "status": "bestanden",
      "sollfelder": 8,
      "abweichungen": 0,
      "fields": {
        "Neuer Dateiname": "ok",
        "Lieferant": "ok",
        "Dokumenttyp": "ok",
        "Dokumentdatum": "ok",
        "RECHNR": "ok",
        "KUNDENNR": "ok",
        "BESTELLNR": "ok",
        "GESAMTBETRAG": "ok"
      }
    },
    "mt-0102-simone-hepp-rechnung-20-06-2023-pdf": {
      "datei": "Simone Hepp Rechnung 20.06.2023.pdf",
      "status": "abweichung",
      "sollfelder": 7,
      "abweichungen": 2,
      "fields": {
        "Neuer Dateiname": "abweichung",
        "Lieferant": "abweichung",
        "Dokumenttyp": "ok",
        "Dokumentdatum": "ok",
        "RECHNR": "ok",
        "KUNDENNR": "ok",
        "GESAMTBETRAG": "ok"
      }
    },
    "mt-0103-simone-hepp-vertrag-pdf": {
      "datei": "Simone Hepp Vertrag.pdf",
      "status": "bestanden",
      "sollfelder": 3,
      "abweichungen": 0,
      "fields": {
        "Neuer Dateiname": "ok",
        "Lieferant": "ok",
        "Dokumenttyp": "ok"
      }
    },
    "mt-0104-skyline-therapie-bochum-gmbh-anderes-21-04-2026-": {
      "datei": "Skyline Therapie Bochum GmbH Anderes 21.04.2026.pdf",
      "status": "abweichung",
      "sollfelder": 6,
      "abweichungen": 3,
      "fields": {
        "Neuer Dateiname": "abweichung",
        "Lieferant": "abweichung",
        "Dokumenttyp": "abweichung",
        "Dokumentdatum": "ok",
        "RECHNR": "ok",
        "GESAMTBETRAG": "ok"
      }
    },
    "mt-0105-skyline-therapie-bochum-gmbh-information-15-04-2": {
      "datei": "Skyline Therapie Bochum GmbH Information 15.04.2026.pdf",
      "status": "abweichung",
      "sollfelder": 6,
      "abweichungen": 3,
      "fields": {
        "Neuer Dateiname": "abweichung",
        "Lieferant": "abweichung",
        "Dokumenttyp": "abweichung",
        "Dokumentdatum": "ok",
        "RECHNR": "ok",
        "GESAMTBETRAG": "ok"
      }
    },
    "mt-0106-sparda-bank-west-eg-anderes-29-10-2019-pdf": {
      "datei": "Sparda-Bank West eG Anderes 29.10.2019.pdf",
      "status": "abweichung",
      "sollfelder": 4,
      "abweichungen": 1,
      "fields": {
        "Neuer Dateiname": "ok",
        "Lieferant": "ok",
        "Dokumenttyp": "abweichung",
        "Dokumentdatum": "ok"
      }
    },
    "mt-0107-sparda-bank-west-eg-anderes-30-01-2020-pdf": {
      "datei": "Sparda-Bank West eG Anderes 30.01.2020.pdf",
      "status": "abweichung",
      "sollfelder": 4,
      "abweichungen": 3,
      "fields": {
        "Neuer Dateiname": "abweichung",
        "Lieferant": "abweichung",
        "Dokumenttyp": "abweichung",
        "Dokumentdatum": "ok"
      }
    },
    "mt-0108-sparda-bank-west-eg-information-11-12-2019-pdf": {
      "datei": "Sparda-Bank West eG Information 11.12.2019.pdf",
      "status": "abweichung",
      "sollfelder": 5,
      "abweichungen": 4,
      "fields": {
        "Neuer Dateiname": "abweichung",
        "Lieferant": "abweichung",
        "Dokumenttyp": "abweichung",
        "Dokumentdatum": "ok",
        "KUNDENNR": "abweichung"
      }
    },
    "mt-0109-sparda-bank-west-eg-kontoauszug-03-09-2019-pdf": {
      "datei": "Sparda-Bank West eG Kontoauszug 03.09.2019.pdf",
      "status": "abweichung",
      "sollfelder": 4,
      "abweichungen": 2,
      "fields": {
        "Neuer Dateiname": "abweichung",
        "Lieferant": "abweichung",
        "Dokumenttyp": "ok",
        "Dokumentdatum": "ok"
      }
    },
    "mt-0110-sparkasse-bochum-information-07-09-2018-pdf": {
      "datei": "Sparkasse Bochum Information 07.09.2018.pdf",
      "status": "bestanden",
      "sollfelder": 3,
      "abweichungen": 0,
      "fields": {
        "Neuer Dateiname": "ok",
        "Lieferant": "ok",
        "Dokumenttyp": "ok"
      }
    },
    "mt-0111-sparkasse-bochum-kontoauszug-19-08-2022-pdf": {
      "datei": "Sparkasse Bochum Kontoauszug 19.08.2022.pdf",
      "status": "bestanden",
      "sollfelder": 4,
      "abweichungen": 0,
      "fields": {
        "Neuer Dateiname": "ok",
        "Lieferant": "ok",
        "Dokumenttyp": "ok",
        "Dokumentdatum": "ok"
      }
    },
    "mt-0112-staatsanwaltschaft-anderes-04-11-2019-pdf": {
      "datei": "Staatsanwaltschaft Anderes 04.11.2019.pdf",
      "status": "bestanden",
      "sollfelder": 4,
      "abweichungen": 0,
      "fields": {
        "Neuer Dateiname": "ok",
        "Lieferant": "ok",
        "Dokumenttyp": "ok",
        "Dokumentdatum": "ok"
      }
    },
    "mt-0113-staatsanwaltschaft-information-18-12-2024-pdf": {
      "datei": "Staatsanwaltschaft Information 18.12.2024.pdf",
      "status": "abweichung",
      "sollfelder": 5,
      "abweichungen": 1,
      "fields": {
        "Neuer Dateiname": "ok",
        "Lieferant": "ok",
        "Dokumenttyp": "ok",
        "RECHNR": "ok",
        "AKTENZEICHEN": "abweichung"
      }
    },
    "mt-0114-stadtwerke-bochum-netz-gmbh-information-05-01-20": {
      "datei": "Stadtwerke Bochum Netz GmbH Information 05.01.2024.pdf",
      "status": "abweichung",
      "sollfelder": 4,
      "abweichungen": 2,
      "fields": {
        "Neuer Dateiname": "abweichung",
        "Lieferant": "abweichung",
        "Dokumenttyp": "ok",
        "Dokumentdatum": "ok"
      }
    },
    "mt-0115-techniker-information-18-03-2026-pdf": {
      "datei": "Techniker Information 18.03.2026.pdf",
      "status": "abweichung",
      "sollfelder": 5,
      "abweichungen": 1,
      "fields": {
        "Neuer Dateiname": "ok",
        "Lieferant": "ok",
        "Dokumenttyp": "abweichung",
        "Dokumentdatum": "ok",
        "VERSICHERUNGSNR": "ok"
      }
    },
    "mt-0116-tibisco-haustierservice-information-26-02-2024-p": {
      "datei": "Tibisco Haustierservice Information 26.02.2024.pdf",
      "status": "abweichung",
      "sollfelder": 3,
      "abweichungen": 3,
      "fields": {
        "Neuer Dateiname": "abweichung",
        "Lieferant": "abweichung",
        "Dokumenttyp": "abweichung"
      }
    },
    "mt-0117-tierarzt-dr-med-vet-meike-horn-pdf": {
      "datei": "Tierarzt Dr. med, vet. Meike Horn.pdf",
      "status": "bestanden",
      "sollfelder": 6,
      "abweichungen": 0,
      "fields": {
        "Neuer Dateiname": "ok",
        "Lieferant": "ok",
        "Dokumenttyp": "ok",
        "Dokumentdatum": "ok",
        "RECHNR": "ok",
        "GESAMTBETRAG": "ok"
      }
    },
    "mt-0118-tintenfass-kassenzettel-28-01-2026-pdf": {
      "datei": "Tintenfass Kassenzettel 28.01.2026.pdf",
      "status": "bestanden",
      "sollfelder": 5,
      "abweichungen": 0,
      "fields": {
        "Neuer Dateiname": "ok",
        "Lieferant": "ok",
        "Dokumenttyp": "ok",
        "Dokumentdatum": "ok",
        "GESAMTBETRAG": "ok"
      }
    },
    "mt-0119-u-you-bochum-weitmar-rechnung-07-07-25-pdf": {
      "datei": "U_you Bochum-Weitmar _ Rechnung 07.07.25.pdf",
      "status": "abweichung",
      "sollfelder": 6,
      "abweichungen": 2,
      "fields": {
        "Neuer Dateiname": "abweichung",
        "Lieferant": "abweichung",
        "Dokumenttyp": "ok",
        "Dokumentdatum": "ok",
        "RECHNR": "ok",
        "GESAMTBETRAG": "ok"
      }
    },
    "mt-0120-vfl-bochum-1848-gmbh-co-kgaa-anderes-pdf": {
      "datei": "VfL Bochum 1848 GmbH _ Co. KGaA Anderes.pdf",
      "status": "bestanden",
      "sollfelder": 3,
      "abweichungen": 0,
      "fields": {
        "Neuer Dateiname": "ok",
        "Lieferant": "ok",
        "Dokumenttyp": "ok"
      }
    },
    "mt-0121-vfl-bochum-1848-gmbh-co-kgaa-information-22-05-2": {
      "datei": "VfL Bochum 1848 GmbH _ Co. KGaA Information 22.05.2019.pdf",
      "status": "bestanden",
      "sollfelder": 4,
      "abweichungen": 0,
      "fields": {
        "Neuer Dateiname": "ok",
        "Lieferant": "ok",
        "Dokumenttyp": "ok",
        "Dokumentdatum": "ok"
      }
    },
    "mt-0122-vorwerk-deutschland-stiftung-co-kg-rechnung-03-0": {
      "datei": "Vorwerk Deutschland Stiftung _ Co. KG Rechnung 03.04.2025.pdf",
      "status": "bestanden",
      "sollfelder": 5,
      "abweichungen": 0,
      "fields": {
        "Neuer Dateiname": "ok",
        "Lieferant": "ok",
        "Dokumenttyp": "ok",
        "Dokumentdatum": "ok",
        "GESAMTBETRAG": "ok"
      }
    },
    "mt-0123-vorwerk-deutschland-stiftung-co-kg-rechnung-23-0": {
      "datei": "Vorwerk Deutschland Stiftung _ Co. KG Rechnung 23.06.25.pdf",
      "status": "abweichung",
      "sollfelder": 8,
      "abweichungen": 1,
      "fields": {
        "Neuer Dateiname": "ok",
        "Lieferant": "ok",
        "Dokumenttyp": "ok",
        "Dokumentdatum": "ok",
        "RECHNR": "ok",
        "KUNDENNR": "ok",
        "BESTELLNR": "ok",
        "GESAMTBETRAG": "abweichung"
      }
    },
    "mt-0124-vorwerk-store-bochum-rechnung-26-11-25-pdf": {
      "datei": "Vorwerk Store Bochum Rechnung 26.11.25.pdf",
      "status": "abweichung",
      "sollfelder": 8,
      "abweichungen": 1,
      "fields": {
        "Neuer Dateiname": "ok",
        "Lieferant": "ok",
        "Dokumenttyp": "ok",
        "Dokumentdatum": "ok",
        "RECHNR": "ok",
        "KUNDENNR": "abweichung",
        "BESTELLNR": "ok",
        "GESAMTBETRAG": "ok"
      }
    },
    "mt-0125-weicken-schmidt-gmbh-rechnung-pdf": {
      "datei": "Weicken _ Schmidt GmbH Rechnung.pdf",
      "status": "bestanden",
      "sollfelder": 4,
      "abweichungen": 0,
      "fields": {
        "Neuer Dateiname": "ok",
        "Lieferant": "ok",
        "Dokumenttyp": "ok",
        "GESAMTBETRAG": "ok"
      }
    },
    "mt-0126-westdeutsche-allgemeine-zeitung-information-25-1": {
      "datei": "Westdeutsche Allgemeine Zeitung Information 25.10.2018.pdf",
      "status": "bestanden",
      "sollfelder": 5,
      "abweichungen": 0,
      "fields": {
        "Neuer Dateiname": "ok",
        "Lieferant": "ok",
        "Dokumenttyp": "ok",
        "Dokumentdatum": "ok",
        "KUNDENNR": "ok"
      }
    },
    "mt-0127-rztin-f-r-innere-medizin-anderes-16-04-2026-pdf": {
      "datei": "Ärztin für Innere Medizin Anderes 16.04.2026.pdf",
      "status": "bestanden",
      "sollfelder": 4,
      "abweichungen": 0,
      "fields": {
        "Neuer Dateiname": "ok",
        "Lieferant": "ok",
        "Dokumenttyp": "ok",
        "Dokumentdatum": "ok"
      }
    },
    "mt-0128-information-11-07-2019-pdf": {
      "datei": "一 Information 11.07.2019.pdf",
      "status": "bestanden",
      "sollfelder": 4,
      "abweichungen": 0,
      "fields": {
        "Neuer Dateiname": "ok",
        "Lieferant": "ok",
        "Dokumenttyp": "ok",
        "Dokumentdatum": "ok"
      }
    }
  },
  "fields": {
    "Neuer Dateiname": {
      "checked": 128,
      "ok": 76,
      "abweichung": 52
    },
    "Lieferant": {
      "checked": 124,
      "ok": 84,
      "abweichung": 40
    },
    "Dokumenttyp": {
      "checked": 128,
      "ok": 91,
      "abweichung": 37
    },
    "Dokumentdatum": {
      "checked": 112,
      "ok": 108,
      "abweichung": 4
    },
    "RECHNR": {
      "checked": 60,
      "ok": 39,
      "abweichung": 21
    },
    "AKTENZEICHEN": {
      "checked": 13,
      "ok": 0,
      "abweichung": 13
    },
    "KUNDENNR": {
      "checked": 35,
      "ok": 18,
      "abweichung": 17
    },
    "AUFTRAGNR": {
      "checked": 4,
      "ok": 3,
      "abweichung": 1
    },
    "BESTELLNR": {
      "checked": 9,
      "ok": 8,
      "abweichung": 1
    },
    "LIEFERSCHEINNR": {
      "checked": 3,
      "ok": 2,
      "abweichung": 1
    },
    "VERSICHERUNGSNR": {
      "checked": 15,
      "ok": 9,
      "abweichung": 6
    },
    "GESAMTBETRAG": {
      "checked": 64,
      "ok": 44,
      "abweichung": 20
    }
  }
}